MANIFEST.in
setup.py
bloxroute_gateway.egg-info/PKG-INFO
bloxroute_gateway.egg-info/SOURCES.txt
bloxroute_gateway.egg-info/dependency_links.txt
bloxroute_gateway.egg-info/entry_points.txt
bloxroute_gateway.egg-info/requires.txt
bloxroute_gateway.egg-info/top_level.txt
bxcommon/requirements.txt
bxcommon/src/bxcommon/__init__.py
bxcommon/src/bxcommon/common_init_tasks.py
bxcommon/src/bxcommon/common_opts.py
bxcommon/src/bxcommon/constants.py
bxcommon/src/bxcommon/exceptions.py
bxcommon/src/bxcommon/log_messages.py
bxcommon/src/bxcommon/node_runner.py
bxcommon/src/bxcommon/connections/__init__.py
bxcommon/src/bxcommon/connections/abstract_connection.py
bxcommon/src/bxcommon/connections/abstract_feed_connection.py
bxcommon/src/bxcommon/connections/abstract_node.py
bxcommon/src/bxcommon/connections/connection_pool.py
bxcommon/src/bxcommon/connections/connection_state.py
bxcommon/src/bxcommon/connections/connection_type.py
bxcommon/src/bxcommon/connections/internal_node_connection.py
bxcommon/src/bxcommon/feed/__init__.py
bxcommon/src/bxcommon/feed/feed.py
bxcommon/src/bxcommon/feed/feed_manager.py
bxcommon/src/bxcommon/feed/feed_source.py
bxcommon/src/bxcommon/feed/filter_parsing.py
bxcommon/src/bxcommon/feed/new_block_feed.py
bxcommon/src/bxcommon/feed/new_transaction_feed.py
bxcommon/src/bxcommon/feed/proxy_feed.py
bxcommon/src/bxcommon/feed/raw_block.py
bxcommon/src/bxcommon/feed/subscriber.py
bxcommon/src/bxcommon/feed/transaction_status_feed.py
bxcommon/src/bxcommon/feed/eth/__init__.py
bxcommon/src/bxcommon/feed/eth/eth_filter_handlers.py
bxcommon/src/bxcommon/feed/eth/eth_new_transaction_feed.py
bxcommon/src/bxcommon/feed/eth/eth_pending_transaction_feed.py
bxcommon/src/bxcommon/feed/eth/eth_raw_transaction.py
bxcommon/src/bxcommon/feed/eth/eth_transaction_feed_entry.py
bxcommon/src/bxcommon/feed/eth/eth_transaction_no_signature_feed_entry.py
bxcommon/src/bxcommon/feed/eth/eth_transaction_proxy_feed.py
bxcommon/src/bxcommon/messages/__init__.py
bxcommon/src/bxcommon/messages/abstract_block_message.py
bxcommon/src/bxcommon/messages/abstract_internal_message.py
bxcommon/src/bxcommon/messages/abstract_message.py
bxcommon/src/bxcommon/messages/abstract_message_factory.py
