Metadata-Version: 2.1
Name: bloxroute-gateway
Version: 1.109.9
Summary: bloXroute network gateway for scaling blockchains
Home-page: https://bloxroute.com
Author: bloXroute Labs
Author-email: support@bloxroute.com
License: MIT
Platform: UNKNOWN
Classifier: Programming Language :: Python :: 3.6
Classifier: Programming Language :: Python :: 3.7
Classifier: Development Status :: 4 - Beta
Classifier: License :: OSI Approved :: MIT License
Requires-Python: ~=3.6
